alwayson/__init__.py
alwayson/_native.cpython-312-aarch64-linux-gnu.so
alwayson_py-0.6.0.dist-info/METADATA
alwayson_py-0.6.0.dist-info/WHEEL
alwayson_py-0.6.0.dist-info/licenses/LICENSE
alwayson_py-0.6.0.dist-info/RECORD
