Metadata-Version: 2.4
Name: alwayson_py
Version: 0.6.0
Classifier: Development Status :: 3 - Alpha
Classifier: Intended Audience :: Developers
Classifier: License :: OSI Approved :: MIT License
Classifier: Programming Language :: Python :: 3
Classifier: Programming Language :: Python :: 3.8
Classifier: Programming Language :: Python :: 3.9
Classifier: Programming Language :: Python :: 3.10
Classifier: Programming Language :: Python :: 3.11
Classifier: Programming Language :: Python :: 3.12
Classifier: Programming Language :: Rust
Classifier: Topic :: Communications
Classifier: Topic :: Internet
Classifier: Topic :: Software Development :: Libraries :: Python Modules
Requires-Dist: avro-python3>=1.10.2
Requires-Dist: pytest>=7.0 ; extra == 'dev'
Requires-Dist: pytest-asyncio>=0.21 ; extra == 'dev'
Requires-Dist: black>=23.0 ; extra == 'dev'
Requires-Dist: isort>=5.12 ; extra == 'dev'
Requires-Dist: mypy>=1.0 ; extra == 'dev'
Requires-Dist: ruff>=0.1 ; extra == 'dev'
Provides-Extra: dev
License-File: LICENSE
Summary: Python bindings for ThingWorx AlwaysOn protocol encoding/decoding
Keywords: thingworx,iot,protocol,alwayson,codec
Home-Page: https://github.com/xudesheng/alwayson_py
Author-email: Desheng Xu <xudesheng@gmail.com>
Requires-Python: >=3.8
Project-URL: Homepage, https://github.com/xudesheng/alwayson_py
Project-URL: Repository, https://github.com/xudesheng/alwayson_py
Project-URL: Documentation, https://github.com/xudesheng/alwayson_py/blob/main/README.md
Project-URL: Bug Tracker, https://github.com/xudesheng/alwayson_py/issues
